setup.py
pkulogin/__init__.py
pkulogin.egg-info/PKG-INFO
pkulogin.egg-info/SOURCES.txt
pkulogin.egg-info/dependency_links.txt
pkulogin.egg-info/entry_points.txt
pkulogin.egg-info/top_level.txt
pkulogin.egg-info/zip-safe