Metadata-Version: 1.0
Name: pkulogin
Version: 0.1
Summary: login https://its.pku.edu.cn with python
Home-page: UNKNOWN
Author: Yue Liu
Author-email: UNKNOWN
License: MIT
Platform: UNKNOWN
